README.md
setup.py
Oz.egg-info/PKG-INFO
Oz.egg-info/SOURCES.txt
Oz.egg-info/dependency_links.txt
Oz.egg-info/entry_points.txt
Oz.egg-info/not-zip-safe
Oz.egg-info/requires.txt
Oz.egg-info/top_level.txt
oz/__init__.py
oz/cli.py
oz/testing.py
oz/aws_cdn/__init__.py
oz/aws_cdn/actions.py
oz/aws_cdn/middleware.py
oz/aws_cdn/options.py
oz/aws_cdn/uimodules.py
oz/bandit/__init__.py
oz/bandit/actions.py
oz/bandit/middleware.py
oz/blinks/__init__.py
oz/blinks/middleware.py
oz/core/__init__.py
oz/core/actions.py
oz/core/options.py
oz/error_pages/__init__.py
oz/error_pages/middleware.py
oz/error_pages/options.py
oz/error_pages/uimodules.py
oz/json_api/__init__.py
oz/json_api/errors.py
oz/json_api/middleware.py
oz/json_api/options.py
oz/redis/__init__.py
oz/redis/middleware.py
oz/redis/options.py
oz/redis_sessions/__init__.py
oz/redis_sessions/middleware.py
oz/redis_sessions/options.py
oz/skeleton/config.py
oz/skeleton/plugin/__init__.py
oz/skeleton/plugin/handlers.py
oz/skeleton/plugin/models.py
oz/skeleton/plugin/options.py
oz/skeleton/plugin/routes.py
oz/skeleton/plugin/tests/__init__.py
oz/skeleton/plugin/tests/models.py
oz/sqlalchemy/__init__.py
oz/sqlalchemy/actions.py
oz/sqlalchemy/middleware.py
oz/sqlalchemy/options.py