Metadata-Version: 1.0
Name: Oz
Version: 1.2.0
Summary: A batteries-included web framework built on Tornado
Home-page: http://github.com/dailymuse/oz
Author: Yusuf Simonson
Author-email: yusuf@themuse.com
License: UNKNOWN
Platform: UNKNOWN
